pattern_lens/__init__.py
pattern_lens/activations.py
pattern_lens/attn_figure_funcs.py
pattern_lens/consts.py
pattern_lens/figure_util.py
pattern_lens/figures.py
pattern_lens/indexes.py
pattern_lens/load_activations.py
pattern_lens/prompts.py
pattern_lens/py.typed
pattern_lens/server.py
pattern_lens/frontend/patternlens.html
pattern_lens/frontend/pl_cfg.json
pattern_lens/frontend/sg_cfg.json
pattern_lens/frontend/single.html
pattern_lens/frontend/patternlens/app.js
pattern_lens/frontend/patternlens/config.js
pattern_lens/frontend/patternlens/index.html
pattern_lens/frontend/patternlens/style.css
pattern_lens/frontend/patternlens/util.js
pattern_lens/frontend/single/config.js
pattern_lens/frontend/single/dataLoader.js
pattern_lens/frontend/single/index.html
pattern_lens/frontend/single/matrix_png.js
pattern_lens/frontend/single/sg_cfg.json
pattern_lens/frontend/single/style.css
pattern_lens/frontend/single/viewer.js
pattern_lens-0.5.0.dist-info/METADATA
pattern_lens-0.5.0.dist-info/WHEEL
pattern_lens-0.5.0.dist-info/licenses/LICENSE
pattern_lens-0.5.0.dist-info/RECORD
