Metadata-Version: 2.4
Name: pattern_lens
Version: 0.5.0
Project-URL: Homepage, https://miv.name/pattern-lens
Project-URL: Documentation, https://miv.name/pattern-lens
Project-URL: Repository, https://github.com/mivanit/pattern-lens
Project-URL: Issues, https://github.com/mivanit/pattern-lens/issues
License-File: LICENSE
Requires-Python: >=3.11
Requires-Dist: beartype>=0.14.1
Requires-Dist: ipykernel>=6.29.5
Requires-Dist: ipywidgets>=8.1.5
Requires-Dist: jaxtyping>=0.2.33
Requires-Dist: matplotlib>=3.8.0
Requires-Dist: muutils>=0.8.10
Requires-Dist: numpy<2.0.0,>=1.26.1
Requires-Dist: pandas>=2.2.2
Requires-Dist: pillow>=11.0.0
Requires-Dist: scipy>=1.14.1
Requires-Dist: torch>=2.5.1
Requires-Dist: tqdm>=4.66.5
Requires-Dist: transformer-lens>=2.10.0
Requires-Dist: typeguard>=4.4.1
Requires-Dist: zanj>=0.3.1
